LICENSE.md
README.rst
setup.cfg
setup.py
arduino_serial_mux.egg-info/PKG-INFO
arduino_serial_mux.egg-info/SOURCES.txt
arduino_serial_mux.egg-info/dependency_links.txt
arduino_serial_mux.egg-info/entry_points.txt
arduino_serial_mux.egg-info/requires.txt
arduino_serial_mux.egg-info/top_level.txt
serial_mux/__init__.py
serial_mux/cli.py
serial_mux/serial_mux.py
serial_mux/vserial.py