Metadata-Version: 2.1
Name: arduino-serial-mux
Version: 1.1.0
Summary: Arduino serial port multiplexer.
Home-page: https://arduino-serial-mux.readthedocs.io
Author: Jeroen F.J. Laros
Author-email: jlaros@fixedpoint.nl
License: MIT
Platform: UNKNOWN
Classifier: Intended Audience :: Developers
Classifier: Intended Audience :: Science/Research
Classifier: Operating System :: OS Independent
Classifier: Programming Language :: Python
Classifier: Programming Language :: Python :: 3
Classifier: Topic :: Scientific/Engineering
License-File: LICENSE.md
